MANIFEST.in
README.md
setup.py
django_datafactory/__init__.py
django_datafactory/models.py
django_datafactory/settings.py
django_datafactory/wrappers.py
django_datafactory.egg-info/PKG-INFO
django_datafactory.egg-info/SOURCES.txt
django_datafactory.egg-info/dependency_links.txt
django_datafactory.egg-info/not-zip-safe
django_datafactory.egg-info/requires.txt
django_datafactory.egg-info/top_level.txt